configurationutil/__init__.py
configurationutil/_metadata.py
configurationutil/configuration.py
configurationutil/master_config_schema.json
configurationutil/master_config_template.json
configurationutil/cfg_objects/__init__.py
configurationutil/cfg_objects/_constants.py
configurationutil/cfg_objects/cfg_item.py
configurationutil/cfg_objects/cfg_items.py
configurationutil/cfg_objects/container_cfg_item.py
configurationutil/cfg_objects/inheritable_cfg_item.py
configurationutil/cfg_objects/register.py
configurationutil/cfg_providers/__init__.py
configurationutil/cfg_providers/base_provider.py
configurationutil/cfg_providers/commented_yaml_provider.py
configurationutil/cfg_providers/json_provider.py
configurationutil/cfg_providers/json_provider_default.json
configurationutil/cfg_providers/yaml_provider.py
configurationutil/cfg_providers/yaml_provider_default.yaml
configurationutil/gui/__init__.py
configurationutil/gui/add_edit.py
configurationutil/gui/add_edit_inheritable.py
configurationutil/gui/config_launcher.py
configurationutil/gui/selector.py
configurationutil/gui/params/__init__.py
configurationutil/gui/params/_constants.py
configurationutil/gui/params/base_params_frame.py
configurationutil/gui/params/button.py
configurationutil/gui/params/dict_frame.py
configurationutil/gui/params/list_frame.py
configurationutil/gui/params/window.py
configurationutil/unittests/__init__.py
configurationutil/unittests/test_configuration.py
configurationutil/unittests/test_cfg_objects/__init__.py
configurationutil/unittests/test_cfg_objects/container_objects.py
configurationutil/unittests/test_cfg_objects/inheritable_objects.py
configurationutil/unittests/test_cfg_objects/test_cfg_item.py
configurationutil/unittests/test_cfg_objects/test_cfg_items.py
configurationutil/unittests/test_cfg_objects/test_container_cfg_item.py
configurationutil/unittests/test_cfg_objects/test_inheritable_cfg_item.py
configurationutil/unittests/test_cfg_objects/test_inheritable_cfg_items.py
configurationutil-3.7.6.dist-info/LICENSE.txt
configurationutil-3.7.6.dist-info/METADATA
configurationutil-3.7.6.dist-info/WHEEL
configurationutil-3.7.6.dist-info/entry_points.txt
configurationutil-3.7.6.dist-info/top_level.txt
configurationutil-3.7.6.dist-info/RECORD
