Metadata-Version: 2.1
Name: configurationutil
Version: 3.7.6
Summary: Provides a unified configuration interface.
Home-page: https://bitbucket.org/davisowb/configurationutil.git
Author: Oli Davis
Author-email: oli.davis@me.com, hywel.thomas@mac.com
License: MIT
Download-URL: https://bitbucket.org/davisowb/configurationutil.git/get/3.7.6.tar
Keywords: configuration,config
Platform: UNKNOWN
Classifier: Development Status :: 3 - Alpha
Classifier: Intended Audience :: Developers
Classifier: License :: OSI Approved :: MIT License
Classifier: Programming Language :: Python :: 2
Classifier: Programming Language :: Python :: 2.7
Classifier: Programming Language :: Python :: 3
Classifier: Programming Language :: Python :: 3.6
Classifier: Topic :: Utilities
License-File: LICENSE.txt
Requires-Dist: future (>=0.16.0)
Requires-Dist: appdirs (>=1.4.0)
Requires-Dist: jsonschema (==2.5.1)
Requires-Dist: fdutil (>=1.16.0)
Requires-Dist: logging-helper (>=1.9.0)
Requires-Dist: classutils (>=1.18.1)
Requires-Dist: PyYaml (>=5.3)
Requires-Dist: uiutil (>=1.38.0)
Provides-Extra: test
Requires-Dist: uiutil (>=1.36.4) ; extra == 'test'
Provides-Extra: ui
Requires-Dist: uiutil (>=1.36.4) ; extra == 'ui'
